df2tables/__init__.py
df2tables/comnt.py
df2tables/datatable_templ.html
df2tables/df2tables.py
df2tables/tablepl.py
df2tables-0.2.1.dist-info/METADATA
df2tables-0.2.1.dist-info/WHEEL
df2tables-0.2.1.dist-info/licenses/LICENSE
df2tables-0.2.1.dist-info/RECORD
