Metadata-Version: 2.4
Name: df2tables
Version: 0.2.1
Summary: df2tables: Pandas and Polars DataFrames to Interactive DataTables
Project-URL: Homepage, https://github.com/ts-kontakt/df2tables
Project-URL: Issues, https://github.com/ts-kontakt/df2tables/issues
Author-email: Tomasz Sługocki <ts.kontakt@gmail.com>
License: MIT License
License-File: LICENSE
Keywords: DataTables,HTML,Javascript,Pandas,Polars
Provides-Extra: pandas
Requires-Dist: pandas; extra == 'pandas'
Provides-Extra: polars
Requires-Dist: polars; extra == 'polars'
